lightkube/__init__.py
lightkube/codecs.py
lightkube/config/__init__.py
lightkube/config/client_adapter.py
lightkube/config/kubeconfig.py
lightkube/config/models.py
lightkube/core/__init__.py
lightkube/core/async_client.py
lightkube/core/client.py
lightkube/core/dataclasses_dict.py
lightkube/core/exceptions.py
lightkube/core/generic_client.py
lightkube/core/internal_models.py
lightkube/core/internal_resources.py
lightkube/core/resource.py
lightkube/core/resource_registry.py
lightkube/core/schema.py
lightkube/core/selector.py
lightkube/core/sort_objects.py
lightkube/core/typing_extra.py
lightkube/exceptions.py
lightkube/generic_resource.py
lightkube/operators.py
lightkube/py.typed
lightkube/types.py
lightkube/utils/__init__.py
lightkube/utils/quantity.py
lightkube-0.19.1.dist-info/licenses/LICENSE
lightkube-0.19.1.dist-info/WHEEL
lightkube-0.19.1.dist-info/METADATA
lightkube-0.19.1.dist-info/RECORD
