Metadata-Version: 2.4
Name: lightkube
Version: 0.19.1
Summary: Lightweight kubernetes client library
Author: Giuseppe Tribulato
Author-email: Giuseppe Tribulato <gtsystem@gmail.com>
License-Expression: MIT
License-File: LICENSE
Classifier: Development Status :: 4 - Beta
Classifier: Intended Audience :: Developers
Classifier: Intended Audience :: System Administrators
Classifier: Programming Language :: Python :: 3.8
Classifier: Programming Language :: Python :: 3.9
Classifier: Programming Language :: Python :: 3.10
Classifier: Programming Language :: Python :: 3.11
Classifier: Programming Language :: Python :: 3.12
Classifier: Programming Language :: Python :: 3.13
Classifier: Programming Language :: Python :: 3.14
Requires-Dist: lightkube-models>=1.15.12.0
Requires-Dist: httpx[http2]>=0.28.1,<1.0.0
Requires-Dist: pyyaml
Requires-Dist: jinja2 ; extra == 'jinja-templates'
Requires-Python: >=3.8
Project-URL: Repository, https://github.com/gtsystem/lightkube
Provides-Extra: jinja-templates
